{"updated": "2026-07-21T04:21:42.142934+00:00", "data": {"0-0": {"temp": 16, "code": 0, "wind": 3, "windDeg": 164, "rain": 0}, "0-1": {"temp": 22, "code": 0, "wind": 4, "windDeg": 307, "rain": 0}, "0-2": {"temp": 26, "code": 0, "wind": 4, "windDeg": 265, "rain": 0}, "1-0": {"temp": 19, "code": 3, "wind": 2, "windDeg": 37, "rain": 0}, "1-1": {"temp": 19, "code": 3, "wind": 9, "windDeg": 157, "rain": 10}, "1-2": {"temp": 19, "code": 3, "wind": 10, "windDeg": 322, "rain": 12}, "2-0": {"temp": 12, "code": 0, "wind": 5, "windDeg": 324, "rain": 0}, "2-1": {"temp": 15, "code": 0, "wind": 9, "windDeg": 331, "rain": 0}, "2-2": {"temp": 20, "code": 1, "wind": 7, "windDeg": 313, "rain": 0}, "3-0": {"temp": 13, "code": 2, "wind": 4, "windDeg": 222, "rain": 0}, "3-1": {"temp": 21, "code": 3, "wind": 8, "windDeg": 146, "rain": 0}, "3-2": {"temp": 21, "code": 3, "wind": 6, "windDeg": 183, "rain": 8}, "4-0": {"temp": 14, "code": 3, "wind": 4, "windDeg": 142, "rain": 69}, "4-1": {"temp": 22, "code": 80, "wind": 5, "windDeg": 153, "rain": 77}, "4-2": {"temp": 18, "code": 3, "wind": 8, "windDeg": 309, "rain": 84}, "5-0": {"temp": 16, "code": 0, "wind": 6, "windDeg": 333, "rain": 47}, "5-1": {"temp": 23, "code": 1, "wind": 2, "windDeg": 315, "rain": 17}, "5-2": {"temp": 30, "code": 1, "wind": 8, "windDeg": 242, "rain": 21}}}